nedrex/__init__.py
nedrex/bicon.py
nedrex/closeness.py
nedrex/common.py
nedrex/core.py
nedrex/decorators.py
nedrex/diamond.py
nedrex/disorder.py
nedrex/domino.py
nedrex/exceptions.py
nedrex/graph.py
nedrex/kpm.py
nedrex/must.py
nedrex/neo4j.py
nedrex/ppi.py
nedrex/relations.py
nedrex/robust.py
nedrex/static.py
nedrex/trustrank.py
nedrex/validation.py
nedrex/variants.py
nedrex/vpd.py
nedrex-0.1.4.dist-info/AUTHORS.rst
nedrex-0.1.4.dist-info/LICENSE
nedrex-0.1.4.dist-info/METADATA
nedrex-0.1.4.dist-info/WHEEL
nedrex-0.1.4.dist-info/top_level.txt
nedrex-0.1.4.dist-info/RECORD
