Metadata-Version: 2.1
Name: nedrex
Version: 0.1.4
Summary: A Python library for interfacing with the NeDRex API
License: MIT
Keywords: nedrex
Classifier: Development Status :: 2 - Pre-Alpha
Classifier: Intended Audience :: Developers
Classifier: License :: OSI Approved :: MIT License
Classifier: Natural Language :: English
Classifier: Programming Language :: Python :: 3
Classifier: Programming Language :: Python :: 3.6
Classifier: Programming Language :: Python :: 3.7
Classifier: Programming Language :: Python :: 3.8
Requires-Python: >=3.6
License-File: LICENSE
License-File: AUTHORS.rst
Requires-Dist: attrs (>=21.4.0)
Requires-Dist: requests (>=2.27.1)
Requires-Dist: cachetools (>=4.2.4)
Requires-Dist: more-itertools (>=8.13.0)
Provides-Extra: lint
Requires-Dist: black (>=22.3.0) ; extra == 'lint'
Requires-Dist: flake8 (>=4.0.1) ; extra == 'lint'
Requires-Dist: pylint (>=2.13.9) ; extra == 'lint'
Requires-Dist: bandit (>=1.7.1) ; extra == 'lint'
Provides-Extra: test
Requires-Dist: pytest (>=7.0.1) ; extra == 'test'
Requires-Dist: pytest-xdist (>=2.5.0) ; extra == 'test'
